AUTHORS
LICENSE
MANIFEST.in
README.rst
setup.py
event/__init__.py
event/admin.py
event/generator.py
event/models.py
event/urls.py
event/views.py
event/fixtures/photosizes.json
event/templates/event/event_detail.html
event/templates/event/event_entryitem_list.html
event/templates/event/inclusion_tags/event_detail.html
event/templates/event/inclusion_tags/event_entryitem_list_wide.html
event/templates/event/inclusion_tags/event_entryitem_listing.html
event/templatetags/__init__.py
event/templatetags/event_inclusion_tags.py
panya_event.egg-info/PKG-INFO
panya_event.egg-info/SOURCES.txt
panya_event.egg-info/dependency_links.txt
panya_event.egg-info/not-zip-safe
panya_event.egg-info/requires.txt
panya_event.egg-info/top_level.txt